[{
  "station": "北京南",
  "arriveTime": null,
  "departTime": "07:20",
  "stay": null
}, {
  "station": "天津南",
  "arriveTime": "07:54",
  "departTime": "07:56",
  "stay": 2
}, {
  "station": "济南西",
  "arriveTime": "8:41",
  "departTime": "8:43",
  "stay": 12
}, 
{
  "station": "曲阜东",
  "arriveTime": "9:51",
  "departTime": "9:53",
  "stay": 2
},
{
  "station": "南京南",
  "arriveTime": "11:51",
  "departTime": "11:53",
  "stay": 2
},
{
  "station": "上海虹桥",
  "arriveTime": "13:08",
  "departTime": null,
  "stay": null
}]